algolibs/__init__.py
algolibs/linked_list.py
algolibs/stack.py
algolibs-0.1.3.dist-info/WHEEL
algolibs-0.1.3.dist-info/METADATA
algolibs-0.1.3.dist-info/RECORD
